MANIFEST.in
README.md
setup.py
docs/HISTORY.txt
izug/__init__.py
izug.seantis.reservation.egg-info/PKG-INFO
izug.seantis.reservation.egg-info/SOURCES.txt
izug.seantis.reservation.egg-info/dependency_links.txt
izug.seantis.reservation.egg-info/entry_points.txt
izug.seantis.reservation.egg-info/namespace_packages.txt
izug.seantis.reservation.egg-info/not-zip-safe
izug.seantis.reservation.egg-info/requires.txt
izug.seantis.reservation.egg-info/top_level.txt
izug/seantis/__init__.py
izug/seantis/reservation/__init__.py
izug/seantis/reservation/configure.zcml
izug/seantis/reservation/import_kitas.py
izug/seantis/reservation/kita.py
izug/seantis/reservation/setuphandler.py
izug/seantis/reservation/sync.sh
izug/seantis/reservation/tests.py
izug/seantis/reservation/upgrades.py
izug/seantis/reservation/version.txt
izug/seantis/reservation/js/form.js
izug/seantis/reservation/locales/izug.seantis.reservation.pot
izug/seantis/reservation/locales/de/LC_MESSAGES/izug.seantis.reservation.po
izug/seantis/reservation/profiles/default/metadata.xml
izug/seantis/reservation/profiles/default/viewlets.xml
izug/seantis/reservation/profiles/kita/browserlayer.xml
izug/seantis/reservation/profiles/kita/jsregistry.xml
izug/seantis/reservation/profiles/kita/metadata.xml
izug/seantis/reservation/templates/address.pt
izug/seantis/reservation/templates/contact.pt
izug/seantis/reservation/templates/info.pt