Metadata-Version: 1.1
Name: izug.seantis.reservation
Version: 0.4
Summary: iZug theme adjustments for seantis.reservation
Home-page: http://svn.plone.org/svn/collective/
Author: UNKNOWN
Author-email: UNKNOWN
License: GPL
Platform: UNKNOWN
Classifier: Programming Language :: Python
